geolib/__init__.py
geolib/errors.py
geolib/geometry/__init__.py
geolib/geometry/one.py
geolib/models/__init__.py
geolib/models/base_data_class.py
geolib/models/base_model.py
geolib/models/base_model_list.py
geolib/models/base_model_structure.py
geolib/models/dfoundations/__init__.py
geolib/models/dfoundations/dfoundations_model.py
geolib/models/dfoundations/dfoundations_parserprovider.py
geolib/models/dfoundations/dfoundations_structures.py
geolib/models/dfoundations/internal.py
geolib/models/dfoundations/internal_soil.py
geolib/models/dfoundations/piles.py
geolib/models/dfoundations/profiles.py
geolib/models/dfoundations/serializer.py
geolib/models/dfoundations/soil_csv/bearing_piles_soils.csv
geolib/models/dfoundations/soil_csv/tension_piles_soils.csv
geolib/models/dfoundations/templates/input.foi.j2
geolib/models/dgeoflow/__init__.py
geolib/models/dgeoflow/dgeoflow_model.py
geolib/models/dgeoflow/dgeoflow_parserprovider.py
geolib/models/dgeoflow/dgeoflow_validator.py
geolib/models/dgeoflow/internal.py
geolib/models/dgeoflow/serializer.py
geolib/models/dgeoflow/utils.py
geolib/models/dseries_parser.py
geolib/models/dsettlement/__init__.py
geolib/models/dsettlement/drain_types.py
geolib/models/dsettlement/drains.py
geolib/models/dsettlement/dsettlement_model.py
geolib/models/dsettlement/dsettlement_parserprovider.py
geolib/models/dsettlement/dsettlement_structures.py
geolib/models/dsettlement/internal.py
geolib/models/dsettlement/internal_soil.py
geolib/models/dsettlement/loads.py
geolib/models/dsettlement/probabilistic_calculation_types.py
geolib/models/dsettlement/serializer.py
geolib/models/dsettlement/templates/input.sli.j2
geolib/models/dsettlement/templates/soil_template.j2
geolib/models/dsheetpiling/__init__.py
geolib/models/dsheetpiling/calculation_options.py
geolib/models/dsheetpiling/constructions.py
geolib/models/dsheetpiling/dsheetpiling_model.py
geolib/models/dsheetpiling/dsheetpiling_parserprovider.py
d_geolib-2.8.0.dist-info/entry_points.txt
d_geolib-2.8.0.dist-info/licenses/LICENSE
d_geolib-2.8.0.dist-info/METADATA
d_geolib-2.8.0.dist-info/WHEEL
d_geolib-2.8.0.dist-info/RECORD
