Metadata-Version: 2.4
Name: d-geolib
Version: 2.8.0
Summary: Python wrappers around the input and output files of the Deltares D-Serie and D-GEO Suite models
License: MIT
License-File: LICENSE
Author: Maarten Pronk
Author-email: maarten.pronk@deltares.nl
Requires-Python: >=3.10,<4.0
Classifier: License :: OSI Approved :: MIT License
Classifier: Programming Language :: Python :: 3
Classifier: Programming Language :: Python :: 3.10
Classifier: Programming Language :: Python :: 3.11
Classifier: Programming Language :: Python :: 3.12
Classifier: Programming Language :: Python :: 3.13
Classifier: Programming Language :: Python :: 3.14
Provides-Extra: server
Requires-Dist: fastapi (>=0.95.1) ; extra == "server"
Requires-Dist: httpx (>=0.24.0,<0.25.0) ; extra == "server"
Requires-Dist: jinja2 (>=3.1.2,<4.0.0)
Requires-Dist: matplotlib (>=3.9.0,<4.0.0)
Requires-Dist: pydantic (>=2.0.0,<3.0.0)
Requires-Dist: pydantic-extra-types (>=2.5.0,<3.0.0)
Requires-Dist: pydantic-settings (>=2.1.0,<3.0.0)
Requires-Dist: python-dotenv (>=1.0.0,<2.0.0)
Requires-Dist: python-multipart (>=0.0.9,<0.0.19) ; extra == "server"
Requires-Dist: requests (>=2.29.0,<3.0.0)
Requires-Dist: shapely (>=2.0.1,<3.0.0)
Requires-Dist: uvicorn (>=0.21.1,<0.22.0) ; extra == "server"
Requires-Dist: zipp (>=3.15.0,<4.0.0)
Project-URL: Documentation, https://deltares.github.io/GEOLib/
Project-URL: Homepage, https://deltares.github.io/GEOLib/
Project-URL: Repository, https://github.com/Deltares/GEOLib
